Workbook

Sheet VAT margin
A3: Car sales - margin scheme
A4: period | B4: 46023 | C4: 46112
A6: Invoice number | B6: Date vehicle purchased | C6: Supplier | D6: Reg number | E6: Purchace price | F6: Date sold | G6: Selling price | H6: Profit
B7: 45839 | D7: FG 456 F | E7: 1000 | F7: 46027 | G7: 1500 | H7: =G7-E7 -> 500
H8: =G8-E8 -> 0
H9: =G9-E9 -> 0
H10: =G10-E10 -> 0
H11: =G11-E11 -> 0
H12: =G12-E12 -> 0
H13: =G13-E13 -> 0
H14: =G14-E14 -> 0
H15: =G15-E15 -> 0
H16: =G16-E16 -> 0
H17: =G17-E17 -> 0
H18: =G18-E18 -> 0
H19: =G19-E19 -> 0
A20: Total | E20: =SUM(E7:E19) -> 1000 | G20: =SUM(G7:G19) -> 1500 | H20: =SUM(H7:H19) -> 500
H22: =H20 -> 500 | I22: VATable profit
H23: =ROUND(H22/6,2) -> 83.33 | I23: Output VAT
B24: Total car sales | C24: =COUNTA(C7:C19) -> 0

Sheet Income
A2: period | B2: 46023 | C2: 46112
A4: Date | B4: type | C4: income excl. VAT | D4: VAT | E4: Total
A5: 46023 | B5: Car FR 152 R | C5: 1200 | D5: 0 | E5: =SUM(C5:D5) -> 1200
A6: 46054 | B6: repairs | C6: 100 | D6: 20 | E6: =SUM(C6:D6) -> 120
B7: VAT margin scheme | C7: =-'VAT margin'!H23 -> -83.33 | D7: 0 | E7: =SUM(C7:D7) -> -83.33 | G7: minus page 'VAT margin' Output VAT
E8: =SUM(C8:D8) -> 0
E9: =SUM(C9:D9) -> 0
E10: =SUM(C10:D10) -> 0
E11: =SUM(C11:D11) -> 0
E12: =SUM(C12:D12) -> 0
E13: =SUM(C13:D13) -> 0
E14: =SUM(C14:D14) -> 0
E15: =SUM(C15:D15) -> 0
A16: Total | C16: =SUM(C5:C15) -> 1216.67 | D16: =SUM(D5:D15) -> 20 | E16: =SUM(E5:E15) -> 1236.67

Sheet Expenses
A3: period | B3: 46023 | C3: 46112
A5: date | B5: suplier | D5: Price excl.VAT | E5: VAT | F5: Total | G5: Type
A6: 46023 | B6: Screwfix | C6: screwdriver | D6: 5 | E6: =D6*0.2 -> 1 | F6: =SUM(D6:E6) -> 6 | G6: Tools
A7: 46024 | B7: John Brown | C7: Delivery | D7: 200 | E7: 0 | F7: =SUM(D7:E7) -> 200 | G7: Delivery
A8: 46025 | C8: Car DHF159 FD | D8: 1000 | E8: 0 | F8: =SUM(D8:E8) -> 1000 | G8: Cost of sales
A16: Total | D16: =SUM(D6:D15) -> 1205 | E16: =SUM(E6:E15) -> 1 | F16: =SUM(F6:F15) -> 1206

Sheet VAT return
B2: period | C2: 46023 | D2: 46112
B4: VAT due on sales and other output | C4: 1 | D4: ='VAT margin'!H23+Income!D16 -> 103.33 | F4: page 'VAT margin' Output VAT + page 'Income" Total VAT
B5: VAT due on intra-community … | C5: 2
B7: Total VAT due | C7: 3 | D7: =D4 -> 103.33
B9: VAT reclaimed on purchases and other inputs | C9: 4 | D9: =Expenses!E16 -> 1 | F9: page 'Expenses' Total VAT
B11: Net VAT to be paid to Customs by you | C11: 5 | D11: =D7-D9 -> 102.33 | F11: if '-' HMRC owe money
B12: (difference between boxes 3 and 4)
B14: Total value of sales | C14: 6 | D14: =Income!C16 -> 1216.67 | F14: page 'Income" income excl. VAT
B16: Total value of purchases | C16: 7 | D16: =Expenses!D16 -> 1205 | F16: page 'Expenses'Price excl.VAT

Sheet SA TR 
A2: For year | B2: 24-25 | C2: !!don't forget to add all 4 periods
A4: Income | B4: =Income!C16-'VAT return'!D11 -> 1114.34 | D4: Page 'Income' Total excl.VAT
A7: Total income | B7: =SUM(B4:B6) -> 1114.34
A9: Expenses | D9: Page 'Expenses' Total excl.VAT
A10: OR (HMRC allow to enter all expenses in one line)
A12: Cost of sales | B12: =Expenses!D16 -> 1205 | D12: all excluding VAT
A13: Delivery
A14: Use of home
A15: Rent
A16: Utility bills
A17: Mileage
A20: Total expenses | B20: =SUM(B12:B19) -> 1205
A24: Profit | B24: =B7-B11 -> 1114.34
A26: Taxes | B26: =(B24-12570)*0.2 -> -2291.132
